{
    "version": "https://jsonfeed.org/version/1",
    "title": "CG_heavenhealer • All posts by \"最小生成树\" tag",
    "description": "",
    "home_page_url": "https://cgheavenhealer.github.io",
    "items": [
        {
            "id": "https://cgheavenhealer.github.io/2021/09/17/2021-9-15-%E6%A8%A1%E6%8B%9F%E8%B5%9B/",
            "url": "https://cgheavenhealer.github.io/2021/09/17/2021-9-15-%E6%A8%A1%E6%8B%9F%E8%B5%9B/",
            "title": "2021.9.15 模拟赛",
            "date_published": "2021-09-17T12:52:52.000Z",
            "content_html": "<h3 id=\"t1\"><a class=\"markdownIt-Anchor\" href=\"#t1\">#</a> T1</h3>\n<p><span class=\"exturl\" data-url=\"aHR0cHM6Ly93d3cuc2p6ZXpvai5jb20vY29udGVzdC8xNDgvcHJvYmxlbS85Nzc=\">【雅礼 2019.10.18T1】wzoi</span></p>\n<p><s>水题</s></p>\n<p>因为每天做题只能做最后一道，所以可以用栈维护看过的题，当这天的推荐和栈顶恰好一致时对答案有 <span class=\"katex\"><span class=\"katex-mathml\"><math xmlns=\"http://www.w3.org/1998/Math/MathML\"><semantics><mrow><mn>10</mn></mrow><annotation encoding=\"application/x-tex\">10</annotation></semantics></math></span><span class=\"katex-html\" aria-hidden=\"true\"><span class=\"base\"><span class=\"strut\" style=\"height:0.64444em;vertical-align:0em;\"></span><span class=\"mord\">1</span><span class=\"mord\">0</span></span></span></span> 的贡献；剩下栈里的元素都是当天没推荐的，最优情况就是看一天、写一天，对答案的贡献是 <span class=\"katex\"><span class=\"katex-mathml\"><math xmlns=\"http://www.w3.org/1998/Math/MathML\"><semantics><mrow><mstyle displaystyle=\"true\" scriptlevel=\"0\"><mfrac><mrow><mi>s</mi><mi mathvariant=\"normal\">.</mi><mi>s</mi><mi>i</mi><mi>z</mi><mi>e</mi><mo stretchy=\"false\">(</mo><mo stretchy=\"false\">)</mo><mo>×</mo><mn>5</mn></mrow><mn>2</mn></mfrac></mstyle></mrow><annotation encoding=\"application/x-tex\">\\dfrac{s.size()\\times 5}{2}</annotation></semantics></math></span><span class=\"katex-html\" aria-hidden=\"true\"><span class=\"base\"><span class=\"strut\" style=\"height:2.113em;vertical-align:-0.686em;\"></span><span class=\"mord\"><span class=\"mopen nulldelimiter\"></span><span class=\"mfrac\"><span class=\"vlist-t vlist-t2\"><span class=\"vlist-r\"><span class=\"vlist\" style=\"height:1.427em;\"><span style=\"top:-2.314em;\"><span class=\"pstrut\" style=\"height:3em;\"></span><span class=\"mord\"><span class=\"mord\">2</span></span></span><span style=\"top:-3.23em;\"><span class=\"pstrut\" style=\"height:3em;\"></span><span class=\"frac-line\" style=\"border-bottom-width:0.04em;\"></span></span><span style=\"top:-3.677em;\"><span class=\"pstrut\" style=\"height:3em;\"></span><span class=\"mord\"><span class=\"mord mathnormal\">s</span><span class=\"mord\">.</span><span class=\"mord mathnormal\">s</span><span class=\"mord mathnormal\">i</span><span class=\"mord mathnormal\" style=\"margin-right:0.04398em;\">z</span><span class=\"mord mathnormal\">e</span><span class=\"mopen\">(</span><span class=\"mclose\">)</span><span class=\"mspace\" style=\"margin-right:0.2222222222222222em;\"></span><span class=\"mbin\">×</span><span class=\"mspace\" style=\"margin-right:0.2222222222222222em;\"></span><span class=\"mord\">5</span></span></span></span><span class=\"vlist-s\">​</span></span><span class=\"vlist-r\"><span class=\"vlist\" style=\"height:0.686em;\"><span></span></span></span></span></span><span class=\"mclose nulldelimiter\"></span></span></span></span></span>。</p>\n<figure class=\"highlight cpp\"><figcaption data-lang=\"C++\"></figcaption><table><tr><td data-num=\"1\"></td><td><pre><span class=\"token macro property\"><span class=\"token directive-hash\">#</span><span class=\"token directive keyword\">include</span> <span class=\"token string\">&lt;bits/stdc++.h></span></span></pre></td></tr><tr><td data-num=\"2\"></td><td><pre><span class=\"token keyword\">using</span> <span class=\"token keyword\">namespace</span> std<span class=\"token punctuation\">;</span></pre></td></tr><tr><td data-num=\"3\"></td><td><pre><span class=\"token macro property\"><span class=\"token directive-hash\">#</span><span class=\"token directive keyword\">define</span> <span class=\"token macro-name\">int</span> <span class=\"token expression\"><span class=\"token keyword\">long</span> <span class=\"token keyword\">long</span></span></span></pre></td></tr><tr><td data-num=\"4\"></td><td><pre><span class=\"token keyword\">const</span> <span class=\"token keyword\">int</span> N <span class=\"token operator\">=</span> <span class=\"token number\">1e6</span> <span class=\"token operator\">+</span> <span class=\"token number\">10</span><span class=\"token punctuation\">;</span></pre></td></tr><tr><td data-num=\"5\"></td><td><pre><span class=\"token keyword\">char</span> s<span class=\"token punctuation\">[</span>N<span class=\"token punctuation\">]</span><span class=\"token punctuation\">;</span></pre></td></tr><tr><td data-num=\"6\"></td><td><pre>stack<span class=\"token operator\">&lt;</span><span class=\"token keyword\">int</span><span class=\"token operator\">></span> stk<span class=\"token punctuation\">;</span></pre></td></tr><tr><td data-num=\"7\"></td><td><pre><span class=\"token keyword\">int</span> ans<span class=\"token punctuation\">;</span></pre></td></tr><tr><td data-num=\"8\"></td><td><pre><span class=\"token keyword\">signed</span> <span class=\"token function\">main</span><span class=\"token punctuation\">(</span><span class=\"token punctuation\">)</span> <span class=\"token punctuation\">&#123;</span></pre></td></tr><tr><td data-num=\"9\"></td><td><pre>    <span class=\"token function\">scanf</span><span class=\"token punctuation\">(</span><span class=\"token string\">\"%s\"</span><span class=\"token punctuation\">,</span> s <span class=\"token operator\">+</span> <span class=\"token number\">1</span><span class=\"token punctuation\">)</span><span class=\"token punctuation\">;</span></pre></td></tr><tr><td data-num=\"10\"></td><td><pre>    <span class=\"token keyword\">int</span> n <span class=\"token operator\">=</span> <span class=\"token function\">strlen</span><span class=\"token punctuation\">(</span>s <span class=\"token operator\">+</span> <span class=\"token number\">1</span><span class=\"token punctuation\">)</span><span class=\"token punctuation\">;</span></pre></td></tr><tr><td data-num=\"11\"></td><td><pre>    stk<span class=\"token punctuation\">.</span><span class=\"token function\">push</span><span class=\"token punctuation\">(</span>s<span class=\"token punctuation\">[</span><span class=\"token number\">1</span><span class=\"token punctuation\">]</span><span class=\"token punctuation\">)</span><span class=\"token punctuation\">;</span></pre></td></tr><tr><td data-num=\"12\"></td><td><pre>    <span class=\"token keyword\">for</span> <span class=\"token punctuation\">(</span><span class=\"token keyword\">int</span> i <span class=\"token operator\">=</span> <span class=\"token number\">2</span><span class=\"token punctuation\">;</span> i <span class=\"token operator\">&lt;=</span> n<span class=\"token punctuation\">;</span> i<span class=\"token operator\">++</span><span class=\"token punctuation\">)</span> <span class=\"token punctuation\">&#123;</span></pre></td></tr><tr><td data-num=\"13\"></td><td><pre>        <span class=\"token keyword\">char</span> c <span class=\"token operator\">=</span> s<span class=\"token punctuation\">[</span>i<span class=\"token punctuation\">]</span><span class=\"token punctuation\">;</span></pre></td></tr><tr><td data-num=\"14\"></td><td><pre>        <span class=\"token keyword\">if</span> <span class=\"token punctuation\">(</span>stk<span class=\"token punctuation\">.</span><span class=\"token function\">empty</span><span class=\"token punctuation\">(</span><span class=\"token punctuation\">)</span><span class=\"token punctuation\">)</span> stk<span class=\"token punctuation\">.</span><span class=\"token function\">push</span><span class=\"token punctuation\">(</span>c<span class=\"token punctuation\">)</span><span class=\"token punctuation\">;</span></pre></td></tr><tr><td data-num=\"15\"></td><td><pre>        <span class=\"token keyword\">else</span> <span class=\"token keyword\">if</span> <span class=\"token punctuation\">(</span>stk<span class=\"token punctuation\">.</span><span class=\"token function\">top</span><span class=\"token punctuation\">(</span><span class=\"token punctuation\">)</span> <span class=\"token operator\">==</span> c<span class=\"token punctuation\">)</span> stk<span class=\"token punctuation\">.</span><span class=\"token function\">pop</span><span class=\"token punctuation\">(</span><span class=\"token punctuation\">)</span><span class=\"token punctuation\">,</span> ans <span class=\"token operator\">+=</span> <span class=\"token number\">10</span><span class=\"token punctuation\">;</span></pre></td></tr><tr><td data-num=\"16\"></td><td><pre>        <span class=\"token keyword\">else</span> stk<span class=\"token punctuation\">.</span><span class=\"token function\">push</span><span class=\"token punctuation\">(</span>c<span class=\"token punctuation\">)</span><span class=\"token punctuation\">;</span></pre></td></tr><tr><td data-num=\"17\"></td><td><pre>    <span class=\"token punctuation\">&#125;</span> </pre></td></tr><tr><td data-num=\"18\"></td><td><pre>    ans <span class=\"token operator\">+=</span> <span class=\"token punctuation\">(</span>stk<span class=\"token punctuation\">.</span><span class=\"token function\">size</span><span class=\"token punctuation\">(</span><span class=\"token punctuation\">)</span> <span class=\"token operator\">/</span> <span class=\"token number\">2</span><span class=\"token punctuation\">)</span> <span class=\"token operator\">*</span> <span class=\"token number\">5</span><span class=\"token punctuation\">;</span></pre></td></tr><tr><td data-num=\"19\"></td><td><pre>    <span class=\"token function\">printf</span><span class=\"token punctuation\">(</span><span class=\"token string\">\"%lld\\n\"</span><span class=\"token punctuation\">,</span> ans<span class=\"token punctuation\">)</span><span class=\"token punctuation\">;</span></pre></td></tr><tr><td data-num=\"20\"></td><td><pre>    <span class=\"token keyword\">return</span> <span class=\"token number\">0</span><span class=\"token punctuation\">;</span></pre></td></tr><tr><td data-num=\"21\"></td><td><pre><span class=\"token punctuation\">&#125;</span></pre></td></tr></table></figure><hr>\n<h3 id=\"t2\"><a class=\"markdownIt-Anchor\" href=\"#t2\">#</a> T2</h3>\n<p><span class=\"exturl\" data-url=\"aHR0cHM6Ly93d3cuc2p6ZXpvai5jb20vY29udGVzdC8xNDgvcHJvYmxlbS85NzI=\">【2019.10 雅礼集训 23 日 pmT1】Divisors</span></p>\n<p>处理出每一个数的约数，然后用  <code>std::map</code>  记录一下每个约数的次数，直接计算即可。</p>\n<figure class=\"highlight cpp\"><figcaption data-lang=\"C++\"></figcaption><table><tr><td data-num=\"1\"></td><td><pre><span class=\"token macro property\"><span class=\"token directive-hash\">#</span><span class=\"token directive keyword\">include</span> <span class=\"token string\">&lt;bits/stdc++.h></span></span></pre></td></tr><tr><td data-num=\"2\"></td><td><pre><span class=\"token keyword\">using</span> <span class=\"token keyword\">namespace</span> std<span class=\"token punctuation\">;</span></pre></td></tr><tr><td data-num=\"3\"></td><td><pre><span class=\"token macro property\"><span class=\"token directive-hash\">#</span><span class=\"token directive keyword\">define</span> <span class=\"token macro-name\">int</span> <span class=\"token expression\"><span class=\"token keyword\">long</span> <span class=\"token keyword\">long</span></span></span></pre></td></tr><tr><td data-num=\"4\"></td><td><pre><span class=\"token keyword\">const</span> <span class=\"token keyword\">int</span> N <span class=\"token operator\">=</span> <span class=\"token number\">8e6</span> <span class=\"token operator\">+</span> <span class=\"token number\">10</span><span class=\"token punctuation\">;</span></pre></td></tr><tr><td data-num=\"5\"></td><td><pre><span class=\"token keyword\">int</span> d<span class=\"token punctuation\">[</span>N<span class=\"token punctuation\">]</span><span class=\"token punctuation\">,</span> tot<span class=\"token punctuation\">,</span> n<span class=\"token punctuation\">,</span> m<span class=\"token punctuation\">,</span> a<span class=\"token punctuation\">[</span>N<span class=\"token punctuation\">]</span><span class=\"token punctuation\">,</span> ans<span class=\"token punctuation\">[</span>N<span class=\"token punctuation\">]</span><span class=\"token punctuation\">;</span></pre></td></tr><tr><td data-num=\"6\"></td><td><pre>unordered_map<span class=\"token operator\">&lt;</span><span class=\"token keyword\">int</span><span class=\"token punctuation\">,</span> <span class=\"token keyword\">int</span><span class=\"token operator\">></span> mp<span class=\"token punctuation\">;</span></pre></td></tr><tr><td data-num=\"7\"></td><td><pre><span class=\"token keyword\">inline</span> <span class=\"token keyword\">void</span> <span class=\"token function\">divide</span><span class=\"token punctuation\">(</span><span class=\"token keyword\">int</span> x<span class=\"token punctuation\">)</span> <span class=\"token punctuation\">&#123;</span></pre></td></tr><tr><td data-num=\"8\"></td><td><pre>    <span class=\"token keyword\">for</span> <span class=\"token punctuation\">(</span><span class=\"token keyword\">int</span> i <span class=\"token operator\">=</span> <span class=\"token number\">1</span><span class=\"token punctuation\">;</span> i <span class=\"token operator\">*</span> i <span class=\"token operator\">&lt;=</span> x<span class=\"token punctuation\">;</span> i<span class=\"token operator\">++</span><span class=\"token punctuation\">)</span> <span class=\"token punctuation\">&#123;</span></pre></td></tr><tr><td data-num=\"9\"></td><td><pre>        <span class=\"token keyword\">if</span> <span class=\"token punctuation\">(</span>x <span class=\"token operator\">%</span> i <span class=\"token operator\">==</span> <span class=\"token number\">0</span><span class=\"token punctuation\">)</span> <span class=\"token punctuation\">&#123;</span></pre></td></tr><tr><td data-num=\"10\"></td><td><pre>            <span class=\"token keyword\">if</span> <span class=\"token punctuation\">(</span>i <span class=\"token operator\">&lt;=</span> n<span class=\"token punctuation\">)</span> d<span class=\"token punctuation\">[</span><span class=\"token operator\">++</span>tot<span class=\"token punctuation\">]</span> <span class=\"token operator\">=</span> i<span class=\"token punctuation\">,</span> mp<span class=\"token punctuation\">[</span>i<span class=\"token punctuation\">]</span><span class=\"token operator\">++</span><span class=\"token punctuation\">;</span></pre></td></tr><tr><td data-num=\"11\"></td><td><pre>            <span class=\"token keyword\">if</span> <span class=\"token punctuation\">(</span>x <span class=\"token operator\">/</span> i <span class=\"token operator\">&lt;=</span> n <span class=\"token operator\">&amp;&amp;</span> i <span class=\"token operator\">*</span> i <span class=\"token operator\">!=</span> x<span class=\"token punctuation\">)</span> d<span class=\"token punctuation\">[</span><span class=\"token operator\">++</span>tot<span class=\"token punctuation\">]</span> <span class=\"token operator\">=</span> x <span class=\"token operator\">/</span> i<span class=\"token punctuation\">,</span> mp<span class=\"token punctuation\">[</span>x <span class=\"token operator\">/</span> i<span class=\"token punctuation\">]</span><span class=\"token operator\">++</span><span class=\"token punctuation\">;</span></pre></td></tr><tr><td data-num=\"12\"></td><td><pre>        <span class=\"token punctuation\">&#125;</span></pre></td></tr><tr><td data-num=\"13\"></td><td><pre>    <span class=\"token punctuation\">&#125;</span></pre></td></tr><tr><td data-num=\"14\"></td><td><pre><span class=\"token punctuation\">&#125;</span></pre></td></tr><tr><td data-num=\"15\"></td><td><pre><span class=\"token keyword\">signed</span> <span class=\"token function\">main</span><span class=\"token punctuation\">(</span><span class=\"token punctuation\">)</span> <span class=\"token punctuation\">&#123;</span></pre></td></tr><tr><td data-num=\"16\"></td><td><pre>    ios<span class=\"token double-colon punctuation\">::</span><span class=\"token function\">sync_with_stdio</span><span class=\"token punctuation\">(</span><span class=\"token boolean\">false</span><span class=\"token punctuation\">)</span><span class=\"token punctuation\">;</span></pre></td></tr><tr><td data-num=\"17\"></td><td><pre>    cin<span class=\"token punctuation\">.</span><span class=\"token function\">tie</span><span class=\"token punctuation\">(</span><span class=\"token constant\">NULL</span><span class=\"token punctuation\">)</span><span class=\"token punctuation\">,</span> cout<span class=\"token punctuation\">.</span><span class=\"token function\">tie</span><span class=\"token punctuation\">(</span><span class=\"token constant\">NULL</span><span class=\"token punctuation\">)</span><span class=\"token punctuation\">;</span></pre></td></tr><tr><td data-num=\"18\"></td><td><pre>    cin <span class=\"token operator\">>></span> n <span class=\"token operator\">>></span> m<span class=\"token punctuation\">;</span></pre></td></tr><tr><td data-num=\"19\"></td><td><pre>    <span class=\"token keyword\">for</span> <span class=\"token punctuation\">(</span><span class=\"token keyword\">int</span> i <span class=\"token operator\">=</span> <span class=\"token number\">1</span><span class=\"token punctuation\">;</span> i <span class=\"token operator\">&lt;=</span> m<span class=\"token punctuation\">;</span> i<span class=\"token operator\">++</span><span class=\"token punctuation\">)</span> <span class=\"token punctuation\">&#123;</span></pre></td></tr><tr><td data-num=\"20\"></td><td><pre>        cin <span class=\"token operator\">>></span> a<span class=\"token punctuation\">[</span>i<span class=\"token punctuation\">]</span><span class=\"token punctuation\">;</span></pre></td></tr><tr><td data-num=\"21\"></td><td><pre>        <span class=\"token function\">divide</span><span class=\"token punctuation\">(</span>a<span class=\"token punctuation\">[</span>i<span class=\"token punctuation\">]</span><span class=\"token punctuation\">)</span><span class=\"token punctuation\">;</span></pre></td></tr><tr><td data-num=\"22\"></td><td><pre>    <span class=\"token punctuation\">&#125;</span></pre></td></tr><tr><td data-num=\"23\"></td><td><pre>    <span class=\"token function\">sort</span><span class=\"token punctuation\">(</span>d <span class=\"token operator\">+</span> <span class=\"token number\">1</span><span class=\"token punctuation\">,</span> d <span class=\"token operator\">+</span> tot <span class=\"token operator\">+</span> <span class=\"token number\">1</span><span class=\"token punctuation\">)</span><span class=\"token punctuation\">;</span></pre></td></tr><tr><td data-num=\"24\"></td><td><pre>    tot <span class=\"token operator\">=</span> <span class=\"token function\">unique</span><span class=\"token punctuation\">(</span>d <span class=\"token operator\">+</span> <span class=\"token number\">1</span><span class=\"token punctuation\">,</span> d <span class=\"token operator\">+</span> tot <span class=\"token operator\">+</span> <span class=\"token number\">1</span><span class=\"token punctuation\">)</span> <span class=\"token operator\">-</span> <span class=\"token punctuation\">(</span>d <span class=\"token operator\">+</span> <span class=\"token number\">1</span><span class=\"token punctuation\">)</span><span class=\"token punctuation\">;</span></pre></td></tr><tr><td data-num=\"25\"></td><td><pre>    ans<span class=\"token punctuation\">[</span><span class=\"token number\">0</span><span class=\"token punctuation\">]</span> <span class=\"token operator\">=</span> n <span class=\"token operator\">-</span> tot<span class=\"token punctuation\">;</span></pre></td></tr><tr><td data-num=\"26\"></td><td><pre>    <span class=\"token keyword\">for</span> <span class=\"token punctuation\">(</span><span class=\"token keyword\">int</span> i <span class=\"token operator\">=</span> <span class=\"token number\">1</span><span class=\"token punctuation\">;</span> i <span class=\"token operator\">&lt;=</span> tot<span class=\"token punctuation\">;</span> i<span class=\"token operator\">++</span><span class=\"token punctuation\">)</span> ans<span class=\"token punctuation\">[</span>mp<span class=\"token punctuation\">[</span>d<span class=\"token punctuation\">[</span>i<span class=\"token punctuation\">]</span><span class=\"token punctuation\">]</span><span class=\"token punctuation\">]</span><span class=\"token operator\">++</span><span class=\"token punctuation\">;</span></pre></td></tr><tr><td data-num=\"27\"></td><td><pre>    <span class=\"token keyword\">for</span> <span class=\"token punctuation\">(</span><span class=\"token keyword\">int</span> i <span class=\"token operator\">=</span> <span class=\"token number\">0</span><span class=\"token punctuation\">;</span> i <span class=\"token operator\">&lt;=</span> m<span class=\"token punctuation\">;</span> i<span class=\"token operator\">++</span><span class=\"token punctuation\">)</span> <span class=\"token function\">printf</span><span class=\"token punctuation\">(</span><span class=\"token string\">\"%lld\\n\"</span><span class=\"token punctuation\">,</span> ans<span class=\"token punctuation\">[</span>i<span class=\"token punctuation\">]</span><span class=\"token punctuation\">)</span><span class=\"token punctuation\">;</span></pre></td></tr><tr><td data-num=\"28\"></td><td><pre>    <span class=\"token keyword\">return</span> <span class=\"token number\">0</span><span class=\"token punctuation\">;</span></pre></td></tr><tr><td data-num=\"29\"></td><td><pre><span class=\"token punctuation\">&#125;</span></pre></td></tr></table></figure><hr>\n<h3 id=\"t3\"><a class=\"markdownIt-Anchor\" href=\"#t3\">#</a> T3</h3>\n<p><span class=\"exturl\" data-url=\"aHR0cHM6Ly93d3cuc2p6ZXpvai5jb20vY29udGVzdC8xNDgvcHJvYmxlbS85NzM=\">【2019.10 雅礼集训 23 日 pmT2】Market</span></p>\n<p>直接跑背包空间不足，那就考虑把 DP 的状态改一下，改为在价值为 <span class=\"katex\"><span class=\"katex-mathml\"><math xmlns=\"http://www.w3.org/1998/Math/MathML\"><semantics><mrow><mi>i</mi></mrow><annotation encoding=\"application/x-tex\">i</annotation></semantics></math></span><span class=\"katex-html\" aria-hidden=\"true\"><span class=\"base\"><span class=\"strut\" style=\"height:0.65952em;vertical-align:0em;\"></span><span class=\"mord mathnormal\">i</span></span></span></span> 时的最小体积，先把询问离线下来，按时间排个序，避免商店不开门，查询时二分找一下 <span class=\"katex\"><span class=\"katex-mathml\"><math xmlns=\"http://www.w3.org/1998/Math/MathML\"><semantics><mrow><mi>q</mi><mo stretchy=\"false\">[</mo><mi>i</mi><mo stretchy=\"false\">]</mo><mi mathvariant=\"normal\">.</mi><mi>v</mi></mrow><annotation encoding=\"application/x-tex\">q[i].v</annotation></semantics></math></span><span class=\"katex-html\" aria-hidden=\"true\"><span class=\"base\"><span class=\"strut\" style=\"height:1em;vertical-align:-0.25em;\"></span><span class=\"mord mathnormal\" style=\"margin-right:0.03588em;\">q</span><span class=\"mopen\">[</span><span class=\"mord mathnormal\">i</span><span class=\"mclose\">]</span><span class=\"mord\">.</span><span class=\"mord mathnormal\" style=\"margin-right:0.03588em;\">v</span></span></span></span> 的后继几位最优答案。</p>\n<figure class=\"highlight cpp\"><figcaption data-lang=\"C++\"></figcaption><table><tr><td data-num=\"1\"></td><td><pre><span class=\"token macro property\"><span class=\"token directive-hash\">#</span><span class=\"token directive keyword\">include</span> <span class=\"token string\">&lt;bits/stdc++.h></span></span></pre></td></tr><tr><td data-num=\"2\"></td><td><pre><span class=\"token keyword\">using</span> <span class=\"token keyword\">namespace</span> std<span class=\"token punctuation\">;</span></pre></td></tr><tr><td data-num=\"3\"></td><td><pre><span class=\"token macro property\"><span class=\"token directive-hash\">#</span><span class=\"token directive keyword\">define</span> <span class=\"token macro-name\">int</span> <span class=\"token expression\"><span class=\"token keyword\">long</span> <span class=\"token keyword\">long</span></span></span></pre></td></tr><tr><td data-num=\"4\"></td><td><pre><span class=\"token keyword\">const</span> <span class=\"token keyword\">int</span> V <span class=\"token operator\">=</span> <span class=\"token number\">300</span><span class=\"token punctuation\">,</span> M <span class=\"token operator\">=</span> <span class=\"token number\">1e5</span> <span class=\"token operator\">+</span> <span class=\"token number\">10</span><span class=\"token punctuation\">;</span></pre></td></tr><tr><td data-num=\"5\"></td><td><pre><span class=\"token keyword\">struct</span> <span class=\"token class-name\">node</span> <span class=\"token punctuation\">&#123;</span></pre></td></tr><tr><td data-num=\"6\"></td><td><pre>    <span class=\"token keyword\">int</span> v<span class=\"token punctuation\">,</span> w<span class=\"token punctuation\">,</span> t<span class=\"token punctuation\">;</span></pre></td></tr><tr><td data-num=\"7\"></td><td><pre>    <span class=\"token keyword\">inline</span> <span class=\"token keyword\">bool</span> <span class=\"token keyword\">operator</span><span class=\"token operator\">&lt;</span><span class=\"token punctuation\">(</span><span class=\"token keyword\">const</span> node <span class=\"token operator\">&amp;</span>x<span class=\"token punctuation\">)</span> <span class=\"token punctuation\">&#123;</span> <span class=\"token keyword\">return</span> t <span class=\"token operator\">&lt;</span> x<span class=\"token punctuation\">.</span>t<span class=\"token punctuation\">;</span> <span class=\"token punctuation\">&#125;</span></pre></td></tr><tr><td data-num=\"8\"></td><td><pre><span class=\"token punctuation\">&#125;</span> a<span class=\"token punctuation\">[</span>M<span class=\"token punctuation\">]</span><span class=\"token punctuation\">;</span></pre></td></tr><tr><td data-num=\"9\"></td><td><pre><span class=\"token keyword\">struct</span> <span class=\"token class-name\">node2</span> <span class=\"token punctuation\">&#123;</span></pre></td></tr><tr><td data-num=\"10\"></td><td><pre>    <span class=\"token keyword\">int</span> t<span class=\"token punctuation\">,</span> v<span class=\"token punctuation\">,</span> id<span class=\"token punctuation\">;</span></pre></td></tr><tr><td data-num=\"11\"></td><td><pre>    <span class=\"token keyword\">inline</span> <span class=\"token keyword\">bool</span> <span class=\"token keyword\">operator</span><span class=\"token operator\">&lt;</span><span class=\"token punctuation\">(</span><span class=\"token keyword\">const</span> node2 <span class=\"token operator\">&amp;</span>x<span class=\"token punctuation\">)</span> <span class=\"token punctuation\">&#123;</span> <span class=\"token keyword\">return</span> t <span class=\"token operator\">&lt;</span> x<span class=\"token punctuation\">.</span>t<span class=\"token punctuation\">;</span> <span class=\"token punctuation\">&#125;</span></pre></td></tr><tr><td data-num=\"12\"></td><td><pre><span class=\"token punctuation\">&#125;</span> q<span class=\"token punctuation\">[</span>M<span class=\"token punctuation\">]</span><span class=\"token punctuation\">;</span></pre></td></tr><tr><td data-num=\"13\"></td><td><pre><span class=\"token keyword\">int</span> n<span class=\"token punctuation\">,</span> m<span class=\"token punctuation\">,</span> f<span class=\"token punctuation\">[</span>M<span class=\"token punctuation\">]</span><span class=\"token punctuation\">,</span> j<span class=\"token punctuation\">,</span> ans<span class=\"token punctuation\">[</span>M<span class=\"token punctuation\">]</span><span class=\"token punctuation\">;</span></pre></td></tr><tr><td data-num=\"14\"></td><td><pre><span class=\"token keyword\">signed</span> <span class=\"token function\">main</span><span class=\"token punctuation\">(</span><span class=\"token punctuation\">)</span> <span class=\"token punctuation\">&#123;</span></pre></td></tr><tr><td data-num=\"15\"></td><td><pre>    ios<span class=\"token double-colon punctuation\">::</span><span class=\"token function\">sync_with_stdio</span><span class=\"token punctuation\">(</span><span class=\"token boolean\">false</span><span class=\"token punctuation\">)</span><span class=\"token punctuation\">;</span></pre></td></tr><tr><td data-num=\"16\"></td><td><pre>    cin<span class=\"token punctuation\">.</span><span class=\"token function\">tie</span><span class=\"token punctuation\">(</span><span class=\"token constant\">NULL</span><span class=\"token punctuation\">)</span><span class=\"token punctuation\">,</span> cout<span class=\"token punctuation\">.</span><span class=\"token function\">tie</span><span class=\"token punctuation\">(</span><span class=\"token constant\">NULL</span><span class=\"token punctuation\">)</span><span class=\"token punctuation\">;</span></pre></td></tr><tr><td data-num=\"17\"></td><td><pre>    cin <span class=\"token operator\">>></span> n <span class=\"token operator\">>></span> m<span class=\"token punctuation\">;</span></pre></td></tr><tr><td data-num=\"18\"></td><td><pre>    <span class=\"token keyword\">for</span> <span class=\"token punctuation\">(</span><span class=\"token keyword\">int</span> i <span class=\"token operator\">=</span> <span class=\"token number\">1</span><span class=\"token punctuation\">;</span> i <span class=\"token operator\">&lt;=</span> n<span class=\"token punctuation\">;</span> i<span class=\"token operator\">++</span><span class=\"token punctuation\">)</span> cin <span class=\"token operator\">>></span> a<span class=\"token punctuation\">[</span>i<span class=\"token punctuation\">]</span><span class=\"token punctuation\">.</span>v <span class=\"token operator\">>></span> a<span class=\"token punctuation\">[</span>i<span class=\"token punctuation\">]</span><span class=\"token punctuation\">.</span>w <span class=\"token operator\">>></span> a<span class=\"token punctuation\">[</span>i<span class=\"token punctuation\">]</span><span class=\"token punctuation\">.</span>t<span class=\"token punctuation\">;</span></pre></td></tr><tr><td data-num=\"19\"></td><td><pre>    <span class=\"token keyword\">for</span> <span class=\"token punctuation\">(</span><span class=\"token keyword\">int</span> i <span class=\"token operator\">=</span> <span class=\"token number\">1</span><span class=\"token punctuation\">;</span> i <span class=\"token operator\">&lt;=</span> m<span class=\"token punctuation\">;</span> i<span class=\"token operator\">++</span><span class=\"token punctuation\">)</span> cin <span class=\"token operator\">>></span> q<span class=\"token punctuation\">[</span>i<span class=\"token punctuation\">]</span><span class=\"token punctuation\">.</span>t <span class=\"token operator\">>></span> q<span class=\"token punctuation\">[</span>i<span class=\"token punctuation\">]</span><span class=\"token punctuation\">.</span>v<span class=\"token punctuation\">,</span> q<span class=\"token punctuation\">[</span>i<span class=\"token punctuation\">]</span><span class=\"token punctuation\">.</span>id <span class=\"token operator\">=</span> i<span class=\"token punctuation\">;</span></pre></td></tr><tr><td data-num=\"20\"></td><td><pre>    <span class=\"token function\">sort</span><span class=\"token punctuation\">(</span>a <span class=\"token operator\">+</span> <span class=\"token number\">1</span><span class=\"token punctuation\">,</span> a <span class=\"token operator\">+</span> n <span class=\"token operator\">+</span> <span class=\"token number\">1</span><span class=\"token punctuation\">)</span><span class=\"token punctuation\">,</span> <span class=\"token function\">sort</span><span class=\"token punctuation\">(</span>q <span class=\"token operator\">+</span> <span class=\"token number\">1</span><span class=\"token punctuation\">,</span> q <span class=\"token operator\">+</span> m <span class=\"token operator\">+</span> <span class=\"token number\">1</span><span class=\"token punctuation\">)</span><span class=\"token punctuation\">;</span></pre></td></tr><tr><td data-num=\"21\"></td><td><pre>    <span class=\"token function\">memset</span><span class=\"token punctuation\">(</span>f<span class=\"token punctuation\">,</span> <span class=\"token number\">0x3f</span><span class=\"token punctuation\">,</span> <span class=\"token keyword\">sizeof</span><span class=\"token punctuation\">(</span>f<span class=\"token punctuation\">)</span><span class=\"token punctuation\">)</span><span class=\"token punctuation\">;</span></pre></td></tr><tr><td data-num=\"22\"></td><td><pre>    f<span class=\"token punctuation\">[</span><span class=\"token number\">0</span><span class=\"token punctuation\">]</span> <span class=\"token operator\">=</span> <span class=\"token number\">0</span><span class=\"token punctuation\">,</span> j <span class=\"token operator\">=</span> <span class=\"token number\">1</span><span class=\"token punctuation\">;</span></pre></td></tr><tr><td data-num=\"23\"></td><td><pre>    <span class=\"token keyword\">for</span> <span class=\"token punctuation\">(</span><span class=\"token keyword\">int</span> i <span class=\"token operator\">=</span> <span class=\"token number\">1</span><span class=\"token punctuation\">;</span> i <span class=\"token operator\">&lt;=</span> m<span class=\"token punctuation\">;</span> i<span class=\"token operator\">++</span><span class=\"token punctuation\">)</span> <span class=\"token punctuation\">&#123;</span></pre></td></tr><tr><td data-num=\"24\"></td><td><pre>        <span class=\"token keyword\">for</span> <span class=\"token punctuation\">(</span><span class=\"token punctuation\">;</span> j <span class=\"token operator\">&lt;=</span> n <span class=\"token operator\">&amp;&amp;</span> a<span class=\"token punctuation\">[</span>j<span class=\"token punctuation\">]</span><span class=\"token punctuation\">.</span>t <span class=\"token operator\">&lt;=</span> q<span class=\"token punctuation\">[</span>i<span class=\"token punctuation\">]</span><span class=\"token punctuation\">.</span>t<span class=\"token punctuation\">;</span> j<span class=\"token operator\">++</span><span class=\"token punctuation\">)</span> <span class=\"token punctuation\">&#123;</span></pre></td></tr><tr><td data-num=\"25\"></td><td><pre>            <span class=\"token keyword\">for</span> <span class=\"token punctuation\">(</span><span class=\"token keyword\">int</span> k <span class=\"token operator\">=</span> n <span class=\"token operator\">*</span> V<span class=\"token punctuation\">;</span> k <span class=\"token operator\">>=</span> a<span class=\"token punctuation\">[</span>j<span class=\"token punctuation\">]</span><span class=\"token punctuation\">.</span>w<span class=\"token punctuation\">;</span> k<span class=\"token operator\">--</span><span class=\"token punctuation\">)</span> f<span class=\"token punctuation\">[</span>k<span class=\"token punctuation\">]</span> <span class=\"token operator\">=</span> <span class=\"token function\">min</span><span class=\"token punctuation\">(</span>f<span class=\"token punctuation\">[</span>k<span class=\"token punctuation\">]</span><span class=\"token punctuation\">,</span> f<span class=\"token punctuation\">[</span>k <span class=\"token operator\">-</span> a<span class=\"token punctuation\">[</span>j<span class=\"token punctuation\">]</span><span class=\"token punctuation\">.</span>w<span class=\"token punctuation\">]</span> <span class=\"token operator\">+</span> a<span class=\"token punctuation\">[</span>j<span class=\"token punctuation\">]</span><span class=\"token punctuation\">.</span>v<span class=\"token punctuation\">)</span><span class=\"token punctuation\">;</span></pre></td></tr><tr><td data-num=\"26\"></td><td><pre>            <span class=\"token keyword\">for</span> <span class=\"token punctuation\">(</span><span class=\"token keyword\">int</span> k <span class=\"token operator\">=</span> n <span class=\"token operator\">*</span> V<span class=\"token punctuation\">;</span> k<span class=\"token punctuation\">;</span> k<span class=\"token operator\">--</span><span class=\"token punctuation\">)</span> f<span class=\"token punctuation\">[</span>k<span class=\"token punctuation\">]</span> <span class=\"token operator\">=</span> <span class=\"token function\">min</span><span class=\"token punctuation\">(</span>f<span class=\"token punctuation\">[</span>k<span class=\"token punctuation\">]</span><span class=\"token punctuation\">,</span> f<span class=\"token punctuation\">[</span>k <span class=\"token operator\">+</span> <span class=\"token number\">1</span><span class=\"token punctuation\">]</span><span class=\"token punctuation\">)</span><span class=\"token punctuation\">;</span></pre></td></tr><tr><td data-num=\"27\"></td><td><pre>        <span class=\"token punctuation\">&#125;</span></pre></td></tr><tr><td data-num=\"28\"></td><td><pre>        ans<span class=\"token punctuation\">[</span>q<span class=\"token punctuation\">[</span>i<span class=\"token punctuation\">]</span><span class=\"token punctuation\">.</span>id<span class=\"token punctuation\">]</span> <span class=\"token operator\">=</span> <span class=\"token function\">upper_bound</span><span class=\"token punctuation\">(</span>f <span class=\"token operator\">+</span> <span class=\"token number\">1</span><span class=\"token punctuation\">,</span> f <span class=\"token operator\">+</span> n <span class=\"token operator\">*</span> V <span class=\"token operator\">+</span> <span class=\"token number\">1</span><span class=\"token punctuation\">,</span> q<span class=\"token punctuation\">[</span>i<span class=\"token punctuation\">]</span><span class=\"token punctuation\">.</span>v<span class=\"token punctuation\">)</span> <span class=\"token operator\">-</span> <span class=\"token punctuation\">(</span>f <span class=\"token operator\">+</span> <span class=\"token number\">1</span><span class=\"token punctuation\">)</span><span class=\"token punctuation\">;</span></pre></td></tr><tr><td data-num=\"29\"></td><td><pre>    <span class=\"token punctuation\">&#125;</span></pre></td></tr><tr><td data-num=\"30\"></td><td><pre>    <span class=\"token keyword\">for</span> <span class=\"token punctuation\">(</span><span class=\"token keyword\">int</span> i <span class=\"token operator\">=</span> <span class=\"token number\">1</span><span class=\"token punctuation\">;</span> i <span class=\"token operator\">&lt;=</span> m<span class=\"token punctuation\">;</span> i<span class=\"token operator\">++</span><span class=\"token punctuation\">)</span> cout <span class=\"token operator\">&lt;&lt;</span> ans<span class=\"token punctuation\">[</span>i<span class=\"token punctuation\">]</span> <span class=\"token operator\">&lt;&lt;</span> <span class=\"token string\">'\\n'</span><span class=\"token punctuation\">;</span></pre></td></tr><tr><td data-num=\"31\"></td><td><pre>    <span class=\"token keyword\">return</span> <span class=\"token number\">0</span><span class=\"token punctuation\">;</span></pre></td></tr><tr><td data-num=\"32\"></td><td><pre><span class=\"token punctuation\">&#125;</span></pre></td></tr></table></figure><hr>\n<h3 id=\"t4\"><a class=\"markdownIt-Anchor\" href=\"#t4\">#</a> T4</h3>\n<p><span class=\"exturl\" data-url=\"aHR0cHM6Ly93d3cuc2p6ZXpvai5jb20vY29udGVzdC8xNDgvcHJvYmxlbS85NzQ=\">【2019.10 雅礼集训 14 日 pmT3】动态数点</span></p>\n<p>可以发现如果一个区间满足条件的话，整个区间的 <span class=\"katex\"><span class=\"katex-mathml\"><math xmlns=\"http://www.w3.org/1998/Math/MathML\"><semantics><mrow><mi>gcd</mi><mo>⁡</mo></mrow><annotation encoding=\"application/x-tex\">\\gcd</annotation></semantics></math></span><span class=\"katex-html\" aria-hidden=\"true\"><span class=\"base\"><span class=\"strut\" style=\"height:0.8888799999999999em;vertical-align:-0.19444em;\"></span><span class=\"mop\"><span style=\"margin-right:0.01389em;\">g</span>cd</span></span></span></span> 应该等于区间最小值。</p>\n<p>可以用 ST 表记录区间 <span class=\"katex\"><span class=\"katex-mathml\"><math xmlns=\"http://www.w3.org/1998/Math/MathML\"><semantics><mrow><mi>gcd</mi><mo>⁡</mo></mrow><annotation encoding=\"application/x-tex\">\\gcd</annotation></semantics></math></span><span class=\"katex-html\" aria-hidden=\"true\"><span class=\"base\"><span class=\"strut\" style=\"height:0.8888799999999999em;vertical-align:-0.19444em;\"></span><span class=\"mop\"><span style=\"margin-right:0.01389em;\">g</span>cd</span></span></span></span> 和区间最小值，二分长度，之后找到每一个符合条件的 <span class=\"katex\"><span class=\"katex-mathml\"><math xmlns=\"http://www.w3.org/1998/Math/MathML\"><semantics><mrow><mi>l</mi></mrow><annotation encoding=\"application/x-tex\">l</annotation></semantics></math></span><span class=\"katex-html\" aria-hidden=\"true\"><span class=\"base\"><span class=\"strut\" style=\"height:0.69444em;vertical-align:0em;\"></span><span class=\"mord mathnormal\" style=\"margin-right:0.01968em;\">l</span></span></span></span> 即可。</p>\n<figure class=\"highlight cpp\"><figcaption data-lang=\"C++\"></figcaption><table><tr><td data-num=\"1\"></td><td><pre><span class=\"token macro property\"><span class=\"token directive-hash\">#</span><span class=\"token directive keyword\">include</span> <span class=\"token string\">&lt;bits/stdc++.h></span></span></pre></td></tr><tr><td data-num=\"2\"></td><td><pre><span class=\"token keyword\">using</span> <span class=\"token keyword\">namespace</span> std<span class=\"token punctuation\">;</span></pre></td></tr><tr><td data-num=\"3\"></td><td><pre><span class=\"token comment\">// #define int long long</span></pre></td></tr><tr><td data-num=\"4\"></td><td><pre><span class=\"token keyword\">const</span> <span class=\"token keyword\">int</span> N <span class=\"token operator\">=</span> <span class=\"token number\">1e6</span> <span class=\"token operator\">+</span> <span class=\"token number\">10</span><span class=\"token punctuation\">;</span></pre></td></tr><tr><td data-num=\"5\"></td><td><pre><span class=\"token keyword\">int</span> a<span class=\"token punctuation\">[</span>N<span class=\"token punctuation\">]</span><span class=\"token punctuation\">,</span> n<span class=\"token punctuation\">;</span></pre></td></tr><tr><td data-num=\"6\"></td><td><pre>vector<span class=\"token operator\">&lt;</span><span class=\"token keyword\">int</span><span class=\"token operator\">></span> ans<span class=\"token punctuation\">;</span></pre></td></tr><tr><td data-num=\"7\"></td><td><pre><span class=\"token keyword\">namespace</span> ST <span class=\"token punctuation\">&#123;</span></pre></td></tr><tr><td data-num=\"8\"></td><td><pre>    <span class=\"token keyword\">int</span> f<span class=\"token punctuation\">[</span>N<span class=\"token punctuation\">]</span><span class=\"token punctuation\">[</span><span class=\"token number\">20</span><span class=\"token punctuation\">]</span><span class=\"token punctuation\">,</span> g<span class=\"token punctuation\">[</span>N<span class=\"token punctuation\">]</span><span class=\"token punctuation\">[</span><span class=\"token number\">20</span><span class=\"token punctuation\">]</span><span class=\"token punctuation\">;</span></pre></td></tr><tr><td data-num=\"9\"></td><td><pre>    <span class=\"token keyword\">inline</span> <span class=\"token keyword\">void</span> <span class=\"token function\">prework</span><span class=\"token punctuation\">(</span><span class=\"token punctuation\">)</span> <span class=\"token punctuation\">&#123;</span></pre></td></tr><tr><td data-num=\"10\"></td><td><pre>        <span class=\"token keyword\">for</span> <span class=\"token punctuation\">(</span><span class=\"token keyword\">int</span> i <span class=\"token operator\">=</span> <span class=\"token number\">1</span><span class=\"token punctuation\">;</span> i <span class=\"token operator\">&lt;=</span> n<span class=\"token punctuation\">;</span> i<span class=\"token operator\">++</span><span class=\"token punctuation\">)</span> f<span class=\"token punctuation\">[</span>i<span class=\"token punctuation\">]</span><span class=\"token punctuation\">[</span><span class=\"token number\">0</span><span class=\"token punctuation\">]</span> <span class=\"token operator\">=</span> g<span class=\"token punctuation\">[</span>i<span class=\"token punctuation\">]</span><span class=\"token punctuation\">[</span><span class=\"token number\">0</span><span class=\"token punctuation\">]</span> <span class=\"token operator\">=</span> a<span class=\"token punctuation\">[</span>i<span class=\"token punctuation\">]</span><span class=\"token punctuation\">;</span></pre></td></tr><tr><td data-num=\"11\"></td><td><pre>        <span class=\"token keyword\">int</span> t <span class=\"token operator\">=</span> <span class=\"token function\">log2</span><span class=\"token punctuation\">(</span>n<span class=\"token punctuation\">)</span><span class=\"token punctuation\">;</span></pre></td></tr><tr><td data-num=\"12\"></td><td><pre>        <span class=\"token keyword\">for</span> <span class=\"token punctuation\">(</span><span class=\"token keyword\">int</span> j <span class=\"token operator\">=</span> <span class=\"token number\">1</span><span class=\"token punctuation\">;</span> j <span class=\"token operator\">&lt;=</span> t<span class=\"token punctuation\">;</span> j<span class=\"token operator\">++</span><span class=\"token punctuation\">)</span></pre></td></tr><tr><td data-num=\"13\"></td><td><pre>            <span class=\"token keyword\">for</span> <span class=\"token punctuation\">(</span><span class=\"token keyword\">int</span> i <span class=\"token operator\">=</span> <span class=\"token number\">1</span><span class=\"token punctuation\">;</span> i <span class=\"token operator\">+</span> <span class=\"token punctuation\">(</span><span class=\"token number\">1</span> <span class=\"token operator\">&lt;&lt;</span> j<span class=\"token punctuation\">)</span> <span class=\"token operator\">-</span> <span class=\"token number\">1</span> <span class=\"token operator\">&lt;=</span> n<span class=\"token punctuation\">;</span> i<span class=\"token operator\">++</span><span class=\"token punctuation\">)</span> <span class=\"token punctuation\">&#123;</span></pre></td></tr><tr><td data-num=\"14\"></td><td><pre>                f<span class=\"token punctuation\">[</span>i<span class=\"token punctuation\">]</span><span class=\"token punctuation\">[</span>j<span class=\"token punctuation\">]</span> <span class=\"token operator\">=</span> <span class=\"token function\">min</span><span class=\"token punctuation\">(</span>f<span class=\"token punctuation\">[</span>i<span class=\"token punctuation\">]</span><span class=\"token punctuation\">[</span>j <span class=\"token operator\">-</span> <span class=\"token number\">1</span><span class=\"token punctuation\">]</span><span class=\"token punctuation\">,</span> f<span class=\"token punctuation\">[</span>i <span class=\"token operator\">+</span> <span class=\"token punctuation\">(</span><span class=\"token number\">1</span> <span class=\"token operator\">&lt;&lt;</span> <span class=\"token punctuation\">(</span>j <span class=\"token operator\">-</span> <span class=\"token number\">1</span><span class=\"token punctuation\">)</span><span class=\"token punctuation\">)</span><span class=\"token punctuation\">]</span><span class=\"token punctuation\">[</span>j <span class=\"token operator\">-</span> <span class=\"token number\">1</span><span class=\"token punctuation\">]</span><span class=\"token punctuation\">)</span><span class=\"token punctuation\">;</span></pre></td></tr><tr><td data-num=\"15\"></td><td><pre>                g<span class=\"token punctuation\">[</span>i<span class=\"token punctuation\">]</span><span class=\"token punctuation\">[</span>j<span class=\"token punctuation\">]</span> <span class=\"token operator\">=</span> <span class=\"token function\">__gcd</span><span class=\"token punctuation\">(</span>g<span class=\"token punctuation\">[</span>i<span class=\"token punctuation\">]</span><span class=\"token punctuation\">[</span>j <span class=\"token operator\">-</span> <span class=\"token number\">1</span><span class=\"token punctuation\">]</span><span class=\"token punctuation\">,</span> g<span class=\"token punctuation\">[</span>i <span class=\"token operator\">+</span> <span class=\"token punctuation\">(</span><span class=\"token number\">1</span> <span class=\"token operator\">&lt;&lt;</span> <span class=\"token punctuation\">(</span>j <span class=\"token operator\">-</span> <span class=\"token number\">1</span><span class=\"token punctuation\">)</span><span class=\"token punctuation\">)</span><span class=\"token punctuation\">]</span><span class=\"token punctuation\">[</span>j <span class=\"token operator\">-</span> <span class=\"token number\">1</span><span class=\"token punctuation\">]</span><span class=\"token punctuation\">)</span><span class=\"token punctuation\">;</span></pre></td></tr><tr><td data-num=\"16\"></td><td><pre>            <span class=\"token punctuation\">&#125;</span></pre></td></tr><tr><td data-num=\"17\"></td><td><pre>    <span class=\"token punctuation\">&#125;</span>  </pre></td></tr><tr><td data-num=\"18\"></td><td><pre>    <span class=\"token keyword\">inline</span> <span class=\"token keyword\">int</span> <span class=\"token function\">query_min</span><span class=\"token punctuation\">(</span><span class=\"token keyword\">int</span> l<span class=\"token punctuation\">,</span> <span class=\"token keyword\">int</span> r<span class=\"token punctuation\">)</span> <span class=\"token punctuation\">&#123;</span></pre></td></tr><tr><td data-num=\"19\"></td><td><pre>        <span class=\"token keyword\">int</span> k <span class=\"token operator\">=</span> <span class=\"token function\">log2</span><span class=\"token punctuation\">(</span>r <span class=\"token operator\">-</span> l <span class=\"token operator\">+</span> <span class=\"token number\">1</span><span class=\"token punctuation\">)</span><span class=\"token punctuation\">;</span></pre></td></tr><tr><td data-num=\"20\"></td><td><pre>        <span class=\"token keyword\">return</span> <span class=\"token function\">min</span><span class=\"token punctuation\">(</span>f<span class=\"token punctuation\">[</span>l<span class=\"token punctuation\">]</span><span class=\"token punctuation\">[</span>k<span class=\"token punctuation\">]</span><span class=\"token punctuation\">,</span> f<span class=\"token punctuation\">[</span>r <span class=\"token operator\">-</span> <span class=\"token punctuation\">(</span><span class=\"token number\">1</span> <span class=\"token operator\">&lt;&lt;</span> k<span class=\"token punctuation\">)</span> <span class=\"token operator\">+</span> <span class=\"token number\">1</span><span class=\"token punctuation\">]</span><span class=\"token punctuation\">[</span>k<span class=\"token punctuation\">]</span><span class=\"token punctuation\">)</span><span class=\"token punctuation\">;</span></pre></td></tr><tr><td data-num=\"21\"></td><td><pre>    <span class=\"token punctuation\">&#125;</span></pre></td></tr><tr><td data-num=\"22\"></td><td><pre>    <span class=\"token keyword\">inline</span> <span class=\"token keyword\">int</span> <span class=\"token function\">query_gcd</span><span class=\"token punctuation\">(</span><span class=\"token keyword\">int</span> l<span class=\"token punctuation\">,</span> <span class=\"token keyword\">int</span> r<span class=\"token punctuation\">)</span> <span class=\"token punctuation\">&#123;</span></pre></td></tr><tr><td data-num=\"23\"></td><td><pre>        <span class=\"token keyword\">int</span> k <span class=\"token operator\">=</span> <span class=\"token function\">log2</span><span class=\"token punctuation\">(</span>r <span class=\"token operator\">-</span> l <span class=\"token operator\">+</span> <span class=\"token number\">1</span><span class=\"token punctuation\">)</span><span class=\"token punctuation\">;</span></pre></td></tr><tr><td data-num=\"24\"></td><td><pre>        <span class=\"token keyword\">return</span> <span class=\"token function\">__gcd</span><span class=\"token punctuation\">(</span>g<span class=\"token punctuation\">[</span>l<span class=\"token punctuation\">]</span><span class=\"token punctuation\">[</span>k<span class=\"token punctuation\">]</span><span class=\"token punctuation\">,</span> g<span class=\"token punctuation\">[</span>r <span class=\"token operator\">-</span> <span class=\"token punctuation\">(</span><span class=\"token number\">1</span> <span class=\"token operator\">&lt;&lt;</span> k<span class=\"token punctuation\">)</span> <span class=\"token operator\">+</span> <span class=\"token number\">1</span><span class=\"token punctuation\">]</span><span class=\"token punctuation\">[</span>k<span class=\"token punctuation\">]</span><span class=\"token punctuation\">)</span><span class=\"token punctuation\">;</span></pre></td></tr><tr><td data-num=\"25\"></td><td><pre>    <span class=\"token punctuation\">&#125;</span></pre></td></tr><tr><td data-num=\"26\"></td><td><pre><span class=\"token punctuation\">&#125;</span></pre></td></tr><tr><td data-num=\"27\"></td><td><pre><span class=\"token keyword\">inline</span> <span class=\"token keyword\">bool</span> <span class=\"token function\">check</span><span class=\"token punctuation\">(</span><span class=\"token keyword\">int</span> x<span class=\"token punctuation\">)</span> <span class=\"token punctuation\">&#123;</span></pre></td></tr><tr><td data-num=\"28\"></td><td><pre>    <span class=\"token keyword\">for</span> <span class=\"token punctuation\">(</span><span class=\"token keyword\">int</span> l <span class=\"token operator\">=</span> <span class=\"token number\">1</span><span class=\"token punctuation\">;</span> l <span class=\"token operator\">+</span> x <span class=\"token operator\">&lt;=</span> n<span class=\"token punctuation\">;</span> l<span class=\"token operator\">++</span><span class=\"token punctuation\">)</span> <span class=\"token punctuation\">&#123;</span></pre></td></tr><tr><td data-num=\"29\"></td><td><pre>        <span class=\"token keyword\">int</span> r <span class=\"token operator\">=</span> l <span class=\"token operator\">+</span> x<span class=\"token punctuation\">;</span></pre></td></tr><tr><td data-num=\"30\"></td><td><pre>        <span class=\"token keyword\">if</span> <span class=\"token punctuation\">(</span><span class=\"token class-name\">ST</span><span class=\"token double-colon punctuation\">::</span><span class=\"token function\">query_min</span><span class=\"token punctuation\">(</span>l<span class=\"token punctuation\">,</span> r<span class=\"token punctuation\">)</span> <span class=\"token operator\">==</span> <span class=\"token class-name\">ST</span><span class=\"token double-colon punctuation\">::</span><span class=\"token function\">query_gcd</span><span class=\"token punctuation\">(</span>l<span class=\"token punctuation\">,</span> r<span class=\"token punctuation\">)</span><span class=\"token punctuation\">)</span> <span class=\"token keyword\">return</span> <span class=\"token boolean\">true</span><span class=\"token punctuation\">;</span></pre></td></tr><tr><td data-num=\"31\"></td><td><pre>    <span class=\"token punctuation\">&#125;</span></pre></td></tr><tr><td data-num=\"32\"></td><td><pre>    <span class=\"token keyword\">return</span> <span class=\"token boolean\">false</span><span class=\"token punctuation\">;</span></pre></td></tr><tr><td data-num=\"33\"></td><td><pre><span class=\"token punctuation\">&#125;</span></pre></td></tr><tr><td data-num=\"34\"></td><td><pre><span class=\"token keyword\">signed</span> <span class=\"token function\">main</span><span class=\"token punctuation\">(</span><span class=\"token punctuation\">)</span> <span class=\"token punctuation\">&#123;</span></pre></td></tr><tr><td data-num=\"35\"></td><td><pre>    ios<span class=\"token double-colon punctuation\">::</span><span class=\"token function\">sync_with_stdio</span><span class=\"token punctuation\">(</span><span class=\"token boolean\">false</span><span class=\"token punctuation\">)</span><span class=\"token punctuation\">;</span></pre></td></tr><tr><td data-num=\"36\"></td><td><pre>    cin<span class=\"token punctuation\">.</span><span class=\"token function\">tie</span><span class=\"token punctuation\">(</span><span class=\"token constant\">NULL</span><span class=\"token punctuation\">)</span><span class=\"token punctuation\">,</span> cout<span class=\"token punctuation\">.</span><span class=\"token function\">tie</span><span class=\"token punctuation\">(</span><span class=\"token constant\">NULL</span><span class=\"token punctuation\">)</span><span class=\"token punctuation\">;</span></pre></td></tr><tr><td data-num=\"37\"></td><td><pre>    cin <span class=\"token operator\">>></span> n<span class=\"token punctuation\">;</span></pre></td></tr><tr><td data-num=\"38\"></td><td><pre>    <span class=\"token keyword\">for</span> <span class=\"token punctuation\">(</span><span class=\"token keyword\">int</span> i <span class=\"token operator\">=</span> <span class=\"token number\">1</span><span class=\"token punctuation\">;</span> i <span class=\"token operator\">&lt;=</span> n<span class=\"token punctuation\">;</span> i<span class=\"token operator\">++</span><span class=\"token punctuation\">)</span> cin <span class=\"token operator\">>></span> a<span class=\"token punctuation\">[</span>i<span class=\"token punctuation\">]</span><span class=\"token punctuation\">;</span></pre></td></tr><tr><td data-num=\"39\"></td><td><pre>    <span class=\"token class-name\">ST</span><span class=\"token double-colon punctuation\">::</span><span class=\"token function\">prework</span><span class=\"token punctuation\">(</span><span class=\"token punctuation\">)</span><span class=\"token punctuation\">;</span></pre></td></tr><tr><td data-num=\"40\"></td><td><pre>    <span class=\"token keyword\">int</span> l <span class=\"token operator\">=</span> <span class=\"token number\">0</span><span class=\"token punctuation\">,</span> r <span class=\"token operator\">=</span> n <span class=\"token operator\">-</span> <span class=\"token number\">1</span><span class=\"token punctuation\">,</span> res <span class=\"token operator\">=</span> <span class=\"token number\">0</span><span class=\"token punctuation\">;</span></pre></td></tr><tr><td data-num=\"41\"></td><td><pre>    <span class=\"token keyword\">while</span> <span class=\"token punctuation\">(</span>l <span class=\"token operator\">&lt;=</span> r<span class=\"token punctuation\">)</span> <span class=\"token punctuation\">&#123;</span></pre></td></tr><tr><td data-num=\"42\"></td><td><pre>        <span class=\"token keyword\">int</span> mid <span class=\"token operator\">=</span> <span class=\"token punctuation\">(</span>l <span class=\"token operator\">+</span> r<span class=\"token punctuation\">)</span> <span class=\"token operator\">>></span> <span class=\"token number\">1</span><span class=\"token punctuation\">;</span></pre></td></tr><tr><td data-num=\"43\"></td><td><pre>        <span class=\"token function\">check</span><span class=\"token punctuation\">(</span>mid<span class=\"token punctuation\">)</span> <span class=\"token operator\">?</span> <span class=\"token punctuation\">(</span>res <span class=\"token operator\">=</span> mid<span class=\"token punctuation\">,</span> l <span class=\"token operator\">=</span> mid <span class=\"token operator\">+</span> <span class=\"token number\">1</span><span class=\"token punctuation\">)</span> <span class=\"token operator\">:</span> r <span class=\"token operator\">=</span> mid <span class=\"token operator\">-</span> <span class=\"token number\">1</span><span class=\"token punctuation\">;</span></pre></td></tr><tr><td data-num=\"44\"></td><td><pre>    <span class=\"token punctuation\">&#125;</span></pre></td></tr><tr><td data-num=\"45\"></td><td><pre>    <span class=\"token keyword\">for</span> <span class=\"token punctuation\">(</span><span class=\"token keyword\">int</span> l <span class=\"token operator\">=</span> <span class=\"token number\">1</span><span class=\"token punctuation\">;</span> l <span class=\"token operator\">+</span> res <span class=\"token operator\">&lt;=</span> n<span class=\"token punctuation\">;</span> l<span class=\"token operator\">++</span><span class=\"token punctuation\">)</span> <span class=\"token punctuation\">&#123;</span></pre></td></tr><tr><td data-num=\"46\"></td><td><pre>        <span class=\"token keyword\">int</span> r <span class=\"token operator\">=</span> l <span class=\"token operator\">+</span> res<span class=\"token punctuation\">;</span></pre></td></tr><tr><td data-num=\"47\"></td><td><pre>        <span class=\"token keyword\">if</span> <span class=\"token punctuation\">(</span><span class=\"token class-name\">ST</span><span class=\"token double-colon punctuation\">::</span><span class=\"token function\">query_min</span><span class=\"token punctuation\">(</span>l<span class=\"token punctuation\">,</span> r<span class=\"token punctuation\">)</span> <span class=\"token operator\">==</span> <span class=\"token class-name\">ST</span><span class=\"token double-colon punctuation\">::</span><span class=\"token function\">query_gcd</span><span class=\"token punctuation\">(</span>l<span class=\"token punctuation\">,</span> r<span class=\"token punctuation\">)</span><span class=\"token punctuation\">)</span> ans<span class=\"token punctuation\">.</span><span class=\"token function\">push_back</span><span class=\"token punctuation\">(</span>l<span class=\"token punctuation\">)</span><span class=\"token punctuation\">;</span></pre></td></tr><tr><td data-num=\"48\"></td><td><pre>    <span class=\"token punctuation\">&#125;</span></pre></td></tr><tr><td data-num=\"49\"></td><td><pre>    cout <span class=\"token operator\">&lt;&lt;</span> ans<span class=\"token punctuation\">.</span><span class=\"token function\">size</span><span class=\"token punctuation\">(</span><span class=\"token punctuation\">)</span> <span class=\"token operator\">&lt;&lt;</span> <span class=\"token string\">' '</span> <span class=\"token operator\">&lt;&lt;</span> res <span class=\"token operator\">&lt;&lt;</span> <span class=\"token string\">'\\n'</span><span class=\"token punctuation\">;</span></pre></td></tr><tr><td data-num=\"50\"></td><td><pre>    <span class=\"token keyword\">for</span> <span class=\"token punctuation\">(</span><span class=\"token keyword\">auto</span> i <span class=\"token operator\">:</span> ans<span class=\"token punctuation\">)</span> cout <span class=\"token operator\">&lt;&lt;</span> i <span class=\"token operator\">&lt;&lt;</span> <span class=\"token string\">'\\n'</span><span class=\"token punctuation\">;</span></pre></td></tr><tr><td data-num=\"51\"></td><td><pre>    <span class=\"token keyword\">return</span> <span class=\"token number\">0</span><span class=\"token punctuation\">;</span></pre></td></tr><tr><td data-num=\"52\"></td><td><pre><span class=\"token punctuation\">&#125;</span></pre></td></tr></table></figure><hr>\n<h3 id=\"t5\"><a class=\"markdownIt-Anchor\" href=\"#t5\">#</a> T5</h3>\n<p><span class=\"exturl\" data-url=\"aHR0cHM6Ly93d3cuc2p6ZXpvai5jb20vY29udGVzdC8xNDgvcHJvYmxlbS85NzU=\">【2019.10 雅礼集训 14 日 pmT1】序列</span></p>\n<p>整个区间移动的话，除了端点，每一个点的增量都是 <span class=\"katex\"><span class=\"katex-mathml\"><math xmlns=\"http://www.w3.org/1998/Math/MathML\"><semantics><mrow><mo>±</mo><mn>1</mn></mrow><annotation encoding=\"application/x-tex\">\\pm1</annotation></semantics></math></span><span class=\"katex-html\" aria-hidden=\"true\"><span class=\"base\"><span class=\"strut\" style=\"height:0.72777em;vertical-align:-0.08333em;\"></span><span class=\"mord\">±</span><span class=\"mord\">1</span></span></span></span>，而正负数对答案的贡献不相同。可以把正负数分开记，记录正负数的个数，以及每个负数需要多少次能够变为非负数，端点特判一下，这些次数的最小值。</p>\n<figure class=\"highlight cpp\"><figcaption data-lang=\"C++\"></figcaption><table><tr><td data-num=\"1\"></td><td><pre><span class=\"token macro property\"><span class=\"token directive-hash\">#</span><span class=\"token directive keyword\">include</span> <span class=\"token string\">&lt;bits/stdc++.h></span></span></pre></td></tr><tr><td data-num=\"2\"></td><td><pre><span class=\"token keyword\">using</span> <span class=\"token keyword\">namespace</span> std<span class=\"token punctuation\">;</span></pre></td></tr><tr><td data-num=\"3\"></td><td><pre><span class=\"token macro property\"><span class=\"token directive-hash\">#</span><span class=\"token directive keyword\">define</span> <span class=\"token macro-name\">int</span> <span class=\"token expression\"><span class=\"token keyword\">long</span> <span class=\"token keyword\">long</span></span></span></pre></td></tr><tr><td data-num=\"4\"></td><td><pre><span class=\"token keyword\">const</span> <span class=\"token keyword\">int</span> N <span class=\"token operator\">=</span> <span class=\"token number\">5e6</span> <span class=\"token operator\">+</span> <span class=\"token number\">10</span><span class=\"token punctuation\">,</span> INF <span class=\"token operator\">=</span> <span class=\"token number\">1e18</span><span class=\"token punctuation\">;</span></pre></td></tr><tr><td data-num=\"5\"></td><td><pre><span class=\"token keyword\">int</span> n<span class=\"token punctuation\">,</span> m<span class=\"token punctuation\">,</span> cnt1<span class=\"token punctuation\">,</span> cnt2<span class=\"token punctuation\">,</span> cnt<span class=\"token punctuation\">[</span>N<span class=\"token punctuation\">]</span><span class=\"token punctuation\">,</span> a<span class=\"token punctuation\">[</span>N<span class=\"token punctuation\">]</span><span class=\"token punctuation\">,</span> ans <span class=\"token operator\">=</span> INF<span class=\"token punctuation\">,</span> sum<span class=\"token punctuation\">;</span></pre></td></tr><tr><td data-num=\"6\"></td><td><pre><span class=\"token keyword\">signed</span> <span class=\"token function\">main</span><span class=\"token punctuation\">(</span><span class=\"token punctuation\">)</span> <span class=\"token punctuation\">&#123;</span></pre></td></tr><tr><td data-num=\"7\"></td><td><pre>    ios<span class=\"token double-colon punctuation\">::</span><span class=\"token function\">sync_with_stdio</span><span class=\"token punctuation\">(</span><span class=\"token boolean\">false</span><span class=\"token punctuation\">)</span><span class=\"token punctuation\">;</span></pre></td></tr><tr><td data-num=\"8\"></td><td><pre>    cin<span class=\"token punctuation\">.</span><span class=\"token function\">tie</span><span class=\"token punctuation\">(</span><span class=\"token constant\">NULL</span><span class=\"token punctuation\">)</span><span class=\"token punctuation\">,</span> cout<span class=\"token punctuation\">.</span><span class=\"token function\">tie</span><span class=\"token punctuation\">(</span><span class=\"token constant\">NULL</span><span class=\"token punctuation\">)</span><span class=\"token punctuation\">;</span></pre></td></tr><tr><td data-num=\"9\"></td><td><pre>    cin <span class=\"token operator\">>></span> n<span class=\"token punctuation\">;</span></pre></td></tr><tr><td data-num=\"10\"></td><td><pre>    <span class=\"token keyword\">for</span> <span class=\"token punctuation\">(</span><span class=\"token keyword\">int</span> i <span class=\"token operator\">=</span> <span class=\"token number\">1</span><span class=\"token punctuation\">;</span> i <span class=\"token operator\">&lt;=</span> n<span class=\"token punctuation\">;</span> i<span class=\"token operator\">++</span><span class=\"token punctuation\">)</span> cin <span class=\"token operator\">>></span> a<span class=\"token punctuation\">[</span>i<span class=\"token punctuation\">]</span><span class=\"token punctuation\">;</span></pre></td></tr><tr><td data-num=\"11\"></td><td><pre>    <span class=\"token keyword\">for</span> <span class=\"token punctuation\">(</span><span class=\"token keyword\">int</span> i <span class=\"token operator\">=</span> <span class=\"token number\">1</span><span class=\"token punctuation\">;</span> i <span class=\"token operator\">&lt;=</span> n<span class=\"token punctuation\">;</span> i<span class=\"token operator\">++</span><span class=\"token punctuation\">)</span> <span class=\"token punctuation\">&#123;</span></pre></td></tr><tr><td data-num=\"12\"></td><td><pre>        <span class=\"token keyword\">int</span> x <span class=\"token operator\">=</span> a<span class=\"token punctuation\">[</span>i<span class=\"token punctuation\">]</span> <span class=\"token operator\">-</span> i<span class=\"token punctuation\">;</span></pre></td></tr><tr><td data-num=\"13\"></td><td><pre>        x <span class=\"token operator\">>=</span> <span class=\"token number\">0</span> <span class=\"token operator\">?</span> <span class=\"token punctuation\">(</span>cnt1<span class=\"token operator\">++</span><span class=\"token punctuation\">,</span> sum <span class=\"token operator\">+=</span> x<span class=\"token punctuation\">)</span> <span class=\"token operator\">:</span> <span class=\"token punctuation\">(</span>cnt2<span class=\"token operator\">++</span><span class=\"token punctuation\">,</span> sum <span class=\"token operator\">+=</span> <span class=\"token operator\">-</span>x<span class=\"token punctuation\">,</span> cnt<span class=\"token punctuation\">[</span><span class=\"token operator\">-</span>x<span class=\"token punctuation\">]</span><span class=\"token operator\">++</span><span class=\"token punctuation\">)</span><span class=\"token punctuation\">;</span></pre></td></tr><tr><td data-num=\"14\"></td><td><pre>    <span class=\"token punctuation\">&#125;</span></pre></td></tr><tr><td data-num=\"15\"></td><td><pre>    <span class=\"token keyword\">for</span> <span class=\"token punctuation\">(</span><span class=\"token keyword\">int</span> i <span class=\"token operator\">=</span> <span class=\"token number\">1</span><span class=\"token punctuation\">;</span> i <span class=\"token operator\">&lt;</span> n<span class=\"token punctuation\">;</span> i<span class=\"token operator\">++</span><span class=\"token punctuation\">)</span> <span class=\"token punctuation\">&#123;</span></pre></td></tr><tr><td data-num=\"16\"></td><td><pre>        <span class=\"token keyword\">int</span> x <span class=\"token operator\">=</span> a<span class=\"token punctuation\">[</span>i<span class=\"token punctuation\">]</span> <span class=\"token operator\">-</span> <span class=\"token number\">1</span><span class=\"token punctuation\">,</span> y <span class=\"token operator\">=</span> a<span class=\"token punctuation\">[</span>i<span class=\"token punctuation\">]</span> <span class=\"token operator\">-</span> n<span class=\"token punctuation\">;</span></pre></td></tr><tr><td data-num=\"17\"></td><td><pre>        cnt1<span class=\"token operator\">--</span><span class=\"token punctuation\">,</span> sum <span class=\"token operator\">-=</span> x<span class=\"token punctuation\">;</span></pre></td></tr><tr><td data-num=\"18\"></td><td><pre>        cnt2<span class=\"token operator\">++</span><span class=\"token punctuation\">,</span> sum <span class=\"token operator\">+=</span> <span class=\"token operator\">-</span>y<span class=\"token punctuation\">,</span> cnt<span class=\"token punctuation\">[</span><span class=\"token operator\">-</span>y <span class=\"token operator\">+</span> i<span class=\"token punctuation\">]</span><span class=\"token operator\">++</span><span class=\"token punctuation\">;</span></pre></td></tr><tr><td data-num=\"19\"></td><td><pre>        sum <span class=\"token operator\">+=</span> cnt1 <span class=\"token operator\">-</span> cnt2 <span class=\"token operator\">+</span> <span class=\"token number\">1</span><span class=\"token punctuation\">;</span></pre></td></tr><tr><td data-num=\"20\"></td><td><pre>        <span class=\"token keyword\">if</span> <span class=\"token punctuation\">(</span>cnt<span class=\"token punctuation\">[</span>i<span class=\"token punctuation\">]</span><span class=\"token punctuation\">)</span> cnt1 <span class=\"token operator\">+=</span> cnt<span class=\"token punctuation\">[</span>i<span class=\"token punctuation\">]</span><span class=\"token punctuation\">,</span> cnt2 <span class=\"token operator\">-=</span> cnt<span class=\"token punctuation\">[</span>i<span class=\"token punctuation\">]</span><span class=\"token punctuation\">;</span></pre></td></tr><tr><td data-num=\"21\"></td><td><pre>        ans <span class=\"token operator\">=</span> <span class=\"token function\">min</span><span class=\"token punctuation\">(</span>ans<span class=\"token punctuation\">,</span> sum<span class=\"token punctuation\">)</span><span class=\"token punctuation\">;</span></pre></td></tr><tr><td data-num=\"22\"></td><td><pre>    <span class=\"token punctuation\">&#125;</span></pre></td></tr><tr><td data-num=\"23\"></td><td><pre>    cout <span class=\"token operator\">&lt;&lt;</span> ans <span class=\"token operator\">&lt;&lt;</span> endl<span class=\"token punctuation\">;</span></pre></td></tr><tr><td data-num=\"24\"></td><td><pre>    <span class=\"token keyword\">return</span> <span class=\"token number\">0</span><span class=\"token punctuation\">;</span></pre></td></tr><tr><td data-num=\"25\"></td><td><pre><span class=\"token punctuation\">&#125;</span></pre></td></tr></table></figure><hr>\n<h3 id=\"t6\"><a class=\"markdownIt-Anchor\" href=\"#t6\">#</a> T6</h3>\n<p><span class=\"exturl\" data-url=\"aHR0cHM6Ly93d3cuc2p6ZXpvai5jb20vY29udGVzdC8xNDgvcHJvYmxlbS84OTE=\">「CCC 2018」最大战略储备</span></p>\n<p>显然岛内直接跑最小生成树即可，关键在怎么连岛屿之间的边。</p>\n<p>可以把边分个类，假设岛内连边是横向，岛与岛连边是纵向，可以先跑横纵一起的最小生成树，再分开跑最小生成树，最后的答案就是总点权减最小生成树的总点权。</p>\n<figure class=\"highlight cpp\"><figcaption data-lang=\"C++\"></figcaption><table><tr><td data-num=\"1\"></td><td><pre><span class=\"token macro property\"><span class=\"token directive-hash\">#</span><span class=\"token directive keyword\">include</span> <span class=\"token string\">&lt;bits/stdc++.h></span></span></pre></td></tr><tr><td data-num=\"2\"></td><td><pre><span class=\"token keyword\">using</span> <span class=\"token keyword\">namespace</span> std<span class=\"token punctuation\">;</span></pre></td></tr><tr><td data-num=\"3\"></td><td><pre><span class=\"token macro property\"><span class=\"token directive-hash\">#</span><span class=\"token directive keyword\">define</span> <span class=\"token macro-name\">int</span> <span class=\"token expression\"><span class=\"token keyword\">long</span> <span class=\"token keyword\">long</span></span></span></pre></td></tr><tr><td data-num=\"4\"></td><td><pre><span class=\"token keyword\">const</span> <span class=\"token keyword\">int</span> N <span class=\"token operator\">=</span> <span class=\"token number\">1e5</span> <span class=\"token operator\">+</span> <span class=\"token number\">10</span><span class=\"token punctuation\">;</span></pre></td></tr><tr><td data-num=\"5\"></td><td><pre><span class=\"token keyword\">struct</span> <span class=\"token class-name\">node</span> <span class=\"token punctuation\">&#123;</span></pre></td></tr><tr><td data-num=\"6\"></td><td><pre>    <span class=\"token keyword\">int</span> u<span class=\"token punctuation\">,</span> v<span class=\"token punctuation\">,</span> w<span class=\"token punctuation\">;</span></pre></td></tr><tr><td data-num=\"7\"></td><td><pre>    <span class=\"token keyword\">inline</span> <span class=\"token keyword\">bool</span> <span class=\"token keyword\">operator</span><span class=\"token operator\">&lt;</span><span class=\"token punctuation\">(</span><span class=\"token keyword\">const</span> node <span class=\"token operator\">&amp;</span>x<span class=\"token punctuation\">)</span> <span class=\"token punctuation\">&#123;</span></pre></td></tr><tr><td data-num=\"8\"></td><td><pre>        <span class=\"token keyword\">return</span> w <span class=\"token operator\">&lt;</span> x<span class=\"token punctuation\">.</span>w<span class=\"token punctuation\">;</span></pre></td></tr><tr><td data-num=\"9\"></td><td><pre>    <span class=\"token punctuation\">&#125;</span></pre></td></tr><tr><td data-num=\"10\"></td><td><pre><span class=\"token punctuation\">&#125;</span> a<span class=\"token punctuation\">[</span>N<span class=\"token punctuation\">]</span><span class=\"token punctuation\">,</span> b<span class=\"token punctuation\">[</span>N<span class=\"token punctuation\">]</span><span class=\"token punctuation\">;</span></pre></td></tr><tr><td data-num=\"11\"></td><td><pre><span class=\"token keyword\">int</span> n<span class=\"token punctuation\">,</span> m<span class=\"token punctuation\">,</span> p<span class=\"token punctuation\">,</span> q<span class=\"token punctuation\">,</span> sum<span class=\"token punctuation\">,</span> x <span class=\"token operator\">=</span> <span class=\"token number\">1</span><span class=\"token punctuation\">,</span> y <span class=\"token operator\">=</span> <span class=\"token number\">1</span><span class=\"token punctuation\">,</span> ans<span class=\"token punctuation\">;</span></pre></td></tr><tr><td data-num=\"12\"></td><td><pre><span class=\"token keyword\">namespace</span> DSU <span class=\"token punctuation\">&#123;</span></pre></td></tr><tr><td data-num=\"13\"></td><td><pre>    <span class=\"token keyword\">int</span> s1<span class=\"token punctuation\">[</span>N<span class=\"token punctuation\">]</span><span class=\"token punctuation\">,</span> s2<span class=\"token punctuation\">[</span>N<span class=\"token punctuation\">]</span><span class=\"token punctuation\">;</span></pre></td></tr><tr><td data-num=\"14\"></td><td><pre>    <span class=\"token keyword\">inline</span> <span class=\"token keyword\">void</span> <span class=\"token function\">init</span><span class=\"token punctuation\">(</span><span class=\"token punctuation\">)</span> <span class=\"token punctuation\">&#123;</span></pre></td></tr><tr><td data-num=\"15\"></td><td><pre>        <span class=\"token keyword\">for</span> <span class=\"token punctuation\">(</span><span class=\"token keyword\">int</span> i <span class=\"token operator\">=</span> <span class=\"token number\">1</span><span class=\"token punctuation\">;</span> i <span class=\"token operator\">&lt;</span> N<span class=\"token punctuation\">;</span> i<span class=\"token operator\">++</span><span class=\"token punctuation\">)</span> s1<span class=\"token punctuation\">[</span>i<span class=\"token punctuation\">]</span> <span class=\"token operator\">=</span> s2<span class=\"token punctuation\">[</span>i<span class=\"token punctuation\">]</span> <span class=\"token operator\">=</span> i<span class=\"token punctuation\">;</span></pre></td></tr><tr><td data-num=\"16\"></td><td><pre>    <span class=\"token punctuation\">&#125;</span></pre></td></tr><tr><td data-num=\"17\"></td><td><pre>    <span class=\"token keyword\">inline</span> <span class=\"token keyword\">int</span> <span class=\"token function\">find1</span><span class=\"token punctuation\">(</span><span class=\"token keyword\">int</span> x<span class=\"token punctuation\">)</span> <span class=\"token punctuation\">&#123;</span></pre></td></tr><tr><td data-num=\"18\"></td><td><pre>        <span class=\"token keyword\">return</span> x <span class=\"token operator\">==</span> s1<span class=\"token punctuation\">[</span>x<span class=\"token punctuation\">]</span> <span class=\"token operator\">?</span> x <span class=\"token operator\">:</span> s1<span class=\"token punctuation\">[</span>x<span class=\"token punctuation\">]</span> <span class=\"token operator\">=</span> <span class=\"token function\">find1</span><span class=\"token punctuation\">(</span>s1<span class=\"token punctuation\">[</span>x<span class=\"token punctuation\">]</span><span class=\"token punctuation\">)</span><span class=\"token punctuation\">;</span></pre></td></tr><tr><td data-num=\"19\"></td><td><pre>    <span class=\"token punctuation\">&#125;</span> </pre></td></tr><tr><td data-num=\"20\"></td><td><pre>    <span class=\"token keyword\">inline</span> <span class=\"token keyword\">int</span> <span class=\"token function\">find2</span><span class=\"token punctuation\">(</span><span class=\"token keyword\">int</span> x<span class=\"token punctuation\">)</span> <span class=\"token punctuation\">&#123;</span></pre></td></tr><tr><td data-num=\"21\"></td><td><pre>        <span class=\"token keyword\">return</span> x <span class=\"token operator\">==</span> s2<span class=\"token punctuation\">[</span>x<span class=\"token punctuation\">]</span> <span class=\"token operator\">?</span> x <span class=\"token operator\">:</span> s2<span class=\"token punctuation\">[</span>x<span class=\"token punctuation\">]</span> <span class=\"token operator\">=</span> <span class=\"token function\">find2</span><span class=\"token punctuation\">(</span>s2<span class=\"token punctuation\">[</span>x<span class=\"token punctuation\">]</span><span class=\"token punctuation\">)</span><span class=\"token punctuation\">;</span></pre></td></tr><tr><td data-num=\"22\"></td><td><pre>    <span class=\"token punctuation\">&#125;</span></pre></td></tr><tr><td data-num=\"23\"></td><td><pre><span class=\"token punctuation\">&#125;</span></pre></td></tr><tr><td data-num=\"24\"></td><td><pre><span class=\"token keyword\">using</span> <span class=\"token keyword\">namespace</span> DSU<span class=\"token punctuation\">;</span></pre></td></tr><tr><td data-num=\"25\"></td><td><pre><span class=\"token keyword\">signed</span> <span class=\"token function\">main</span><span class=\"token punctuation\">(</span><span class=\"token punctuation\">)</span> <span class=\"token punctuation\">&#123;</span></pre></td></tr><tr><td data-num=\"26\"></td><td><pre>    ios<span class=\"token double-colon punctuation\">::</span><span class=\"token function\">sync_with_stdio</span><span class=\"token punctuation\">(</span><span class=\"token boolean\">false</span><span class=\"token punctuation\">)</span><span class=\"token punctuation\">;</span></pre></td></tr><tr><td data-num=\"27\"></td><td><pre>    cin<span class=\"token punctuation\">.</span><span class=\"token function\">tie</span><span class=\"token punctuation\">(</span><span class=\"token constant\">NULL</span><span class=\"token punctuation\">)</span><span class=\"token punctuation\">,</span> cout<span class=\"token punctuation\">.</span><span class=\"token function\">tie</span><span class=\"token punctuation\">(</span><span class=\"token constant\">NULL</span><span class=\"token punctuation\">)</span><span class=\"token punctuation\">;</span></pre></td></tr><tr><td data-num=\"28\"></td><td><pre>    cin <span class=\"token operator\">>></span> n <span class=\"token operator\">>></span> m <span class=\"token operator\">>></span> p <span class=\"token operator\">>></span> q<span class=\"token punctuation\">;</span></pre></td></tr><tr><td data-num=\"29\"></td><td><pre>    <span class=\"token keyword\">for</span> <span class=\"token punctuation\">(</span><span class=\"token keyword\">int</span> i <span class=\"token operator\">=</span> <span class=\"token number\">1</span><span class=\"token punctuation\">;</span> i <span class=\"token operator\">&lt;=</span> p<span class=\"token punctuation\">;</span> i<span class=\"token operator\">++</span><span class=\"token punctuation\">)</span> <span class=\"token punctuation\">&#123;</span></pre></td></tr><tr><td data-num=\"30\"></td><td><pre>        cin <span class=\"token operator\">>></span> a<span class=\"token punctuation\">[</span>i<span class=\"token punctuation\">]</span><span class=\"token punctuation\">.</span>u <span class=\"token operator\">>></span> a<span class=\"token punctuation\">[</span>i<span class=\"token punctuation\">]</span><span class=\"token punctuation\">.</span>v <span class=\"token operator\">>></span> a<span class=\"token punctuation\">[</span>i<span class=\"token punctuation\">]</span><span class=\"token punctuation\">.</span>w<span class=\"token punctuation\">;</span></pre></td></tr><tr><td data-num=\"31\"></td><td><pre>        sum <span class=\"token operator\">+=</span> n <span class=\"token operator\">*</span> a<span class=\"token punctuation\">[</span>i<span class=\"token punctuation\">]</span><span class=\"token punctuation\">.</span>w<span class=\"token punctuation\">;</span></pre></td></tr><tr><td data-num=\"32\"></td><td><pre>    <span class=\"token punctuation\">&#125;</span></pre></td></tr><tr><td data-num=\"33\"></td><td><pre>    <span class=\"token keyword\">for</span> <span class=\"token punctuation\">(</span><span class=\"token keyword\">int</span> i <span class=\"token operator\">=</span> <span class=\"token number\">1</span><span class=\"token punctuation\">;</span> i <span class=\"token operator\">&lt;=</span> q<span class=\"token punctuation\">;</span> i<span class=\"token operator\">++</span><span class=\"token punctuation\">)</span> <span class=\"token punctuation\">&#123;</span></pre></td></tr><tr><td data-num=\"34\"></td><td><pre>        cin <span class=\"token operator\">>></span> b<span class=\"token punctuation\">[</span>i<span class=\"token punctuation\">]</span><span class=\"token punctuation\">.</span>u <span class=\"token operator\">>></span> b<span class=\"token punctuation\">[</span>i<span class=\"token punctuation\">]</span><span class=\"token punctuation\">.</span>v <span class=\"token operator\">>></span> b<span class=\"token punctuation\">[</span>i<span class=\"token punctuation\">]</span><span class=\"token punctuation\">.</span>w<span class=\"token punctuation\">;</span></pre></td></tr><tr><td data-num=\"35\"></td><td><pre>        sum <span class=\"token operator\">+=</span> m <span class=\"token operator\">*</span> b<span class=\"token punctuation\">[</span>i<span class=\"token punctuation\">]</span><span class=\"token punctuation\">.</span>w<span class=\"token punctuation\">;</span></pre></td></tr><tr><td data-num=\"36\"></td><td><pre>    <span class=\"token punctuation\">&#125;</span></pre></td></tr><tr><td data-num=\"37\"></td><td><pre>    <span class=\"token function\">init</span><span class=\"token punctuation\">(</span><span class=\"token punctuation\">)</span><span class=\"token punctuation\">;</span></pre></td></tr><tr><td data-num=\"38\"></td><td><pre>    <span class=\"token function\">sort</span><span class=\"token punctuation\">(</span>a <span class=\"token operator\">+</span> <span class=\"token number\">1</span><span class=\"token punctuation\">,</span> a <span class=\"token operator\">+</span> p <span class=\"token operator\">+</span> <span class=\"token number\">1</span><span class=\"token punctuation\">)</span><span class=\"token punctuation\">;</span></pre></td></tr><tr><td data-num=\"39\"></td><td><pre>    <span class=\"token function\">sort</span><span class=\"token punctuation\">(</span>b <span class=\"token operator\">+</span> <span class=\"token number\">1</span><span class=\"token punctuation\">,</span> b <span class=\"token operator\">+</span> q <span class=\"token operator\">+</span> <span class=\"token number\">1</span><span class=\"token punctuation\">)</span><span class=\"token punctuation\">;</span></pre></td></tr><tr><td data-num=\"40\"></td><td><pre>    <span class=\"token keyword\">while</span> <span class=\"token punctuation\">(</span>m <span class=\"token operator\">></span> <span class=\"token number\">1</span> <span class=\"token operator\">&amp;&amp;</span> n <span class=\"token operator\">></span> <span class=\"token number\">1</span><span class=\"token punctuation\">)</span> <span class=\"token punctuation\">&#123;</span></pre></td></tr><tr><td data-num=\"41\"></td><td><pre>        <span class=\"token keyword\">if</span> <span class=\"token punctuation\">(</span>a<span class=\"token punctuation\">[</span>x<span class=\"token punctuation\">]</span><span class=\"token punctuation\">.</span>w <span class=\"token operator\">&lt;</span> b<span class=\"token punctuation\">[</span>y<span class=\"token punctuation\">]</span><span class=\"token punctuation\">.</span>w<span class=\"token punctuation\">)</span> <span class=\"token punctuation\">&#123;</span></pre></td></tr><tr><td data-num=\"42\"></td><td><pre>            <span class=\"token keyword\">int</span> uu <span class=\"token operator\">=</span> <span class=\"token function\">find1</span><span class=\"token punctuation\">(</span>a<span class=\"token punctuation\">[</span>x<span class=\"token punctuation\">]</span><span class=\"token punctuation\">.</span>u<span class=\"token punctuation\">)</span><span class=\"token punctuation\">,</span> vv <span class=\"token operator\">=</span> <span class=\"token function\">find1</span><span class=\"token punctuation\">(</span>a<span class=\"token punctuation\">[</span>x<span class=\"token punctuation\">]</span><span class=\"token punctuation\">.</span>v<span class=\"token punctuation\">)</span><span class=\"token punctuation\">;</span></pre></td></tr><tr><td data-num=\"43\"></td><td><pre>            <span class=\"token keyword\">if</span> <span class=\"token punctuation\">(</span>uu <span class=\"token operator\">!=</span> vv<span class=\"token punctuation\">)</span> s1<span class=\"token punctuation\">[</span>uu<span class=\"token punctuation\">]</span> <span class=\"token operator\">=</span> vv<span class=\"token punctuation\">,</span> m<span class=\"token operator\">--</span><span class=\"token punctuation\">,</span> ans <span class=\"token operator\">+=</span> n <span class=\"token operator\">*</span> a<span class=\"token punctuation\">[</span>x<span class=\"token punctuation\">]</span><span class=\"token punctuation\">.</span>w<span class=\"token punctuation\">;</span></pre></td></tr><tr><td data-num=\"44\"></td><td><pre>            x<span class=\"token operator\">++</span><span class=\"token punctuation\">;</span></pre></td></tr><tr><td data-num=\"45\"></td><td><pre>        <span class=\"token punctuation\">&#125;</span> <span class=\"token keyword\">else</span> <span class=\"token punctuation\">&#123;</span></pre></td></tr><tr><td data-num=\"46\"></td><td><pre>            <span class=\"token keyword\">int</span> uu <span class=\"token operator\">=</span> <span class=\"token function\">find2</span><span class=\"token punctuation\">(</span>b<span class=\"token punctuation\">[</span>y<span class=\"token punctuation\">]</span><span class=\"token punctuation\">.</span>u<span class=\"token punctuation\">)</span><span class=\"token punctuation\">,</span> vv <span class=\"token operator\">=</span> <span class=\"token function\">find2</span><span class=\"token punctuation\">(</span>b<span class=\"token punctuation\">[</span>y<span class=\"token punctuation\">]</span><span class=\"token punctuation\">.</span>v<span class=\"token punctuation\">)</span><span class=\"token punctuation\">;</span></pre></td></tr><tr><td data-num=\"47\"></td><td><pre>            <span class=\"token keyword\">if</span> <span class=\"token punctuation\">(</span>uu <span class=\"token operator\">!=</span> vv<span class=\"token punctuation\">)</span> s2<span class=\"token punctuation\">[</span>uu<span class=\"token punctuation\">]</span> <span class=\"token operator\">=</span> vv<span class=\"token punctuation\">,</span> n<span class=\"token operator\">--</span><span class=\"token punctuation\">,</span> ans <span class=\"token operator\">+=</span> m <span class=\"token operator\">*</span> b<span class=\"token punctuation\">[</span>y<span class=\"token punctuation\">]</span><span class=\"token punctuation\">.</span>w<span class=\"token punctuation\">;</span></pre></td></tr><tr><td data-num=\"48\"></td><td><pre>            y<span class=\"token operator\">++</span><span class=\"token punctuation\">;</span></pre></td></tr><tr><td data-num=\"49\"></td><td><pre>        <span class=\"token punctuation\">&#125;</span></pre></td></tr><tr><td data-num=\"50\"></td><td><pre>    <span class=\"token punctuation\">&#125;</span> </pre></td></tr><tr><td data-num=\"51\"></td><td><pre>    <span class=\"token keyword\">while</span> <span class=\"token punctuation\">(</span>m <span class=\"token operator\">></span> <span class=\"token number\">1</span><span class=\"token punctuation\">)</span> <span class=\"token punctuation\">&#123;</span></pre></td></tr><tr><td data-num=\"52\"></td><td><pre>        <span class=\"token keyword\">int</span> uu <span class=\"token operator\">=</span> <span class=\"token function\">find1</span><span class=\"token punctuation\">(</span>a<span class=\"token punctuation\">[</span>x<span class=\"token punctuation\">]</span><span class=\"token punctuation\">.</span>u<span class=\"token punctuation\">)</span><span class=\"token punctuation\">,</span> vv <span class=\"token operator\">=</span> <span class=\"token function\">find1</span><span class=\"token punctuation\">(</span>a<span class=\"token punctuation\">[</span>x<span class=\"token punctuation\">]</span><span class=\"token punctuation\">.</span>v<span class=\"token punctuation\">)</span><span class=\"token punctuation\">;</span></pre></td></tr><tr><td data-num=\"53\"></td><td><pre>        <span class=\"token keyword\">if</span> <span class=\"token punctuation\">(</span>uu <span class=\"token operator\">!=</span> vv<span class=\"token punctuation\">)</span> s1<span class=\"token punctuation\">[</span>uu<span class=\"token punctuation\">]</span> <span class=\"token operator\">=</span> vv<span class=\"token punctuation\">,</span> m<span class=\"token operator\">--</span><span class=\"token punctuation\">,</span> ans <span class=\"token operator\">+=</span> a<span class=\"token punctuation\">[</span>x<span class=\"token punctuation\">]</span><span class=\"token punctuation\">.</span>w<span class=\"token punctuation\">;</span></pre></td></tr><tr><td data-num=\"54\"></td><td><pre>        x<span class=\"token operator\">++</span><span class=\"token punctuation\">;</span></pre></td></tr><tr><td data-num=\"55\"></td><td><pre>    <span class=\"token punctuation\">&#125;</span> </pre></td></tr><tr><td data-num=\"56\"></td><td><pre>    <span class=\"token keyword\">while</span> <span class=\"token punctuation\">(</span>n <span class=\"token operator\">></span> <span class=\"token number\">1</span><span class=\"token punctuation\">)</span> <span class=\"token punctuation\">&#123;</span></pre></td></tr><tr><td data-num=\"57\"></td><td><pre>        <span class=\"token keyword\">int</span> uu <span class=\"token operator\">=</span> <span class=\"token function\">find2</span><span class=\"token punctuation\">(</span>b<span class=\"token punctuation\">[</span>y<span class=\"token punctuation\">]</span><span class=\"token punctuation\">.</span>u<span class=\"token punctuation\">)</span><span class=\"token punctuation\">,</span> vv <span class=\"token operator\">=</span> <span class=\"token function\">find2</span><span class=\"token punctuation\">(</span>b<span class=\"token punctuation\">[</span>y<span class=\"token punctuation\">]</span><span class=\"token punctuation\">.</span>v<span class=\"token punctuation\">)</span><span class=\"token punctuation\">;</span></pre></td></tr><tr><td data-num=\"58\"></td><td><pre>        <span class=\"token keyword\">if</span> <span class=\"token punctuation\">(</span>uu <span class=\"token operator\">!=</span> vv<span class=\"token punctuation\">)</span> s2<span class=\"token punctuation\">[</span>uu<span class=\"token punctuation\">]</span> <span class=\"token operator\">=</span> vv<span class=\"token punctuation\">,</span> n<span class=\"token operator\">--</span><span class=\"token punctuation\">,</span> ans <span class=\"token operator\">+=</span> b<span class=\"token punctuation\">[</span>y<span class=\"token punctuation\">]</span><span class=\"token punctuation\">.</span>w<span class=\"token punctuation\">;</span></pre></td></tr><tr><td data-num=\"59\"></td><td><pre>        y<span class=\"token operator\">++</span><span class=\"token punctuation\">;</span></pre></td></tr><tr><td data-num=\"60\"></td><td><pre>    <span class=\"token punctuation\">&#125;</span></pre></td></tr><tr><td data-num=\"61\"></td><td><pre>    cout <span class=\"token operator\">&lt;&lt;</span> sum <span class=\"token operator\">-</span> ans <span class=\"token operator\">&lt;&lt;</span> <span class=\"token string\">'\\n'</span><span class=\"token punctuation\">;</span></pre></td></tr><tr><td data-num=\"62\"></td><td><pre>    <span class=\"token keyword\">return</span> <span class=\"token number\">0</span><span class=\"token punctuation\">;</span></pre></td></tr><tr><td data-num=\"63\"></td><td><pre><span class=\"token punctuation\">&#125;</span></pre></td></tr></table></figure>",
            "tags": [
                "数学",
                "贪心",
                "DP",
                "栈",
                "二分",
                "并查集",
                "最小生成树",
                "ST表"
            ]
        }
    ]
}